Workbook
Name anos: Planilha_Investimentos!$D$11
Name aporte: Planilha_Investimentos!$D$10
Name dividendos: Planilha_Investimentos!$D$14
Name patrimonio: Planilha_Investimentos!$D$13
Name redimentos_carteira: Planilha_Investimentos!$D$6
Name rendimento_mensal: Planilha_Investimentos!$D$12
Name salario: Planilha_Investimentos!$D$5
Name sugestao_investimento: Planilha_Investimentos!$D$7
Name taxa_mensal: Planilha_Investimentos!$D$12

Sheet Planilha_Investimentos
B4: CONFIGURAÇÕES
B5: Salário | D5: 2500
B6: Rendimento de Carteira | D6: 0.01
B7: Sugestão de Investimento | D7: =D5*30% -> 750
B9: INVESTIMENTO MENSAL
B10: Quanto investir por mês? | D10: 750
B11: Por quantos anos? | D11: 1
B12: Taxa de rendimento mensal? | D12: 0.0108
B13: Patrimônio acumulado? | D13: =FV(D12,D11*12,D10*-1) -> 9554.3215
B14: Dividendos mensais? | D14: =D13*1% -> 95.543215
B16: CENÁRIOS | D16: DIVIDENDO
A17: 2 | B17: Quanto em 2 anos? | C17: =FV(D12,A17*12,D10*-1) -> 20423.148 | D17: =C17*D6 -> 204.23148
A18: 5 | B18: Quanto em 5 anos? | C18: =FV(D12,A18*12,D10*-1) -> 62853.015 | D18: =C18*D6 -> 628.53015
A19: 10 | B19: Quanto em 10 anos? | C19: =FV(D12,A19*12,D10*-1) -> 182593.25 | D19: =C19*D6 -> 1825.9325
A20: 20 | B20: Quanto em 20 anos? | C20: =FV(D12,A20*12,D10*-1) -> 845286.74 | D20: =C20*D6 -> 8452.8674
A21: 30 | B21: Quanto em 30 anos? | C21: =FV(D12,A21*12,D10*-1) -> 3250428.6 | D21: =C21*D6 -> 32504.286
B23: PERFIL | C23: Conservador
B24: VALOR A SER VENDIDO POR MÊS | C24: =aporte -> 750
B26: TIPO DE FII | C26: PERCENTUAL SUGERIDO | D26: VALORES
B27: PAPEL | C27: =VLOOKUP($C$23&"-"&B27,Planilha_Apoio!$B:$E,4,FALSE) -> 0.3 | D27: =C24*C27 -> 225
B28: TIJOLO | C28: =VLOOKUP($C$23&"-"&B28,Planilha_Apoio!$B:$E,4,FALSE) -> 0.5 | D28: =C24*C28 -> 375
B29: HÍBRIDOS | C29: =VLOOKUP($C$23&"-"&B29,Planilha_Apoio!$B:$E,4,FALSE) -> 0.1 | D29: =C24*C29 -> 75
B30: FOFs | C30: =VLOOKUP($C$23&"-"&B30,Planilha_Apoio!$B:$E,4,FALSE) -> 0.1 | D30: =C24*C30 -> 75
B31: DESENVOLVIMENTO | C31: =VLOOKUP($C$23&"-"&B31,Planilha_Apoio!$B:$E,4,FALSE) -> 0 | D31: =C24*C31 -> 0
B32: HOTELARIAS | C32: =VLOOKUP($C$23&"-"&B32,Planilha_Apoio!$B:$E,4,FALSE) -> 0 | D32: =C24*C32 -> 0
B33: TOTAL | D33: =SUM(D27:D32) -> 750

Sheet Planilha_Apoio
B2: CHAVE | C2: PERFIL | D2: TIPO DE FII | E2: PERCENTUAL SUGERIDO
B3: =C3&"-"&D3 -> Conservador-PAPEL | C3: Conservador | D3: PAPEL | E3: 0.3
B4: =C4&"-"&D4 -> Conservador-TIJOLO | C4: Conservador | D4: TIJOLO | E4: 0.5
B5: =C5&"-"&D5 -> Conservador-HÍBRIDOS | C5: Conservador | D5: HÍBRIDOS | E5: 0.1
B6: =C6&"-"&D6 -> Conservador-FOFs | C6: Conservador | D6: FOFs | E6: 0.1
B7: =C7&"-"&D7 -> Conservador-DESENVOLVIMENTO | C7: Conservador | D7: DESENVOLVIMENTO | E7: 0
B8: =C8&"-"&D8 -> Conservador-HOTELARIAS | C8: Conservador | D8: HOTELARIAS | E8: 0
B10: =C10&"-"&D10 -> Moderado-PAPEL | C10: Moderado | D10: PAPEL | E10: 0.32
B11: =C11&"-"&D11 -> Moderado-TIJOLO | C11: Moderado | D11: TIJOLO | E11: 0.4
B12: =C12&"-"&D12 -> Moderado-HÍBRIDOS | C12: Moderado | D12: HÍBRIDOS | E12: 0.08
B13: =C13&"-"&D13 -> Moderado-FOFs | C13: Moderado | D13: FOFs | E13: 0
B14: =C14&"-"&D14 -> Moderado-DESENVOLVIMENTO | C14: Moderado | D14: DESENVOLVIMENTO | E14: 0.1
B15: =C15&"-"&D15 -> Moderado-HOTELARIAS | C15: Moderado | D15: HOTELARIAS | E15: 0.1
... B22: =C22&"-"&D22 -> Agressivo-HOTELARIAS | C22: Agressivo | D22: HOTELARIAS | E22: 0.1
